tittles/__init__.py
tittles/mod.py
tittles/mod_op.py
tittles/tittles.py
tittles-1.0.0.dist-info/LICENSE
tittles-1.0.0.dist-info/METADATA
tittles-1.0.0.dist-info/WHEEL
tittles-1.0.0.dist-info/top_level.txt
tittles-1.0.0.dist-info/RECORD
