Metadata-Version: 2.1
Name: tittles
Version: 1.0.0
Summary: A package with a lot smal helpful things
Home-page: https://github.com/leonmaks/tittles
Author: Leon
Author-email: le_ma_@mail.ru
License: UNKNOWN
Platform: UNKNOWN
Classifier: Programming Language :: Python :: 3
Classifier: License :: OSI Approved :: MIT License
Classifier: Operating System :: OS Independent
